vines/__init__.py
vines/core/__init__.py
vines/core/application.py
vines/core/exceptions.py
vines/http/__init__.py
vines/http/exceptions.py
vines/http/requests.py
vines/http/responses.py
vines/http/status.py
vines/http/utils.py
vines/middleware/__init__.py
vines/middleware/base.py
vines/middleware/error.py
vines/routing/__init__.py
vines/routing/base.py
vines/routing/converters.py
vines/routing/utils.py
vines-0.1.0.dist-info/METADATA
vines-0.1.0.dist-info/WHEEL
vines-0.1.0.dist-info/licenses/LICENSE
vines-0.1.0.dist-info/RECORD
