Metadata-Version: 2.3
Name: vines
Version: 0.1.0
Summary: A lightweight, high-performance Python Web Framework built on the ASGI standard.
Project-URL: Homepage, https://github.com/spyel/vines
Project-URL: Issues, https://github.com/spyel/vines/issues
Author: sypel
License: MIT License
License-File: LICENSE
Requires-Python: >=3.10
